{
  "$schema": "http://json-schema.org/draft-07/schema#",
  "title": "rules-as-tests rules manifest",
  "type": "object",
  "patternProperties": {
    "^(R[0-9]+[a-z]?|IR[0-9]+)$": {
      "type": "object",
      "required": ["title", "stack", "check", "examples"],
      "additionalProperties": false,
      "properties": {
        "title": { "type": "string", "minLength": 5 },
        "stack": {
          "type": "array",
          "items": { "enum": ["ts-server", "react-next", "microservices"] },
          "minItems": 1
        },
        "applies-to": {
          "type": "array",
          "items": { "type": "string" },
          "description": "Glob patterns, e.g. src/web/handlers/**"
        },
        "requires-package": {
          "type": ["string", "array"],
          "description": "npm package(s) that must be in dependencies for this rule to be applicable. If absent in consumer's package.json and auto-skip-if-missing is true, rule is SKIPPED."
        },
        "auto-skip-if-missing": { "type": "boolean", "default": false },
        "check": {
          "oneOf": [
            { "type": "object", "required": ["type", "rule"], "properties": {
              "type": { "const": "eslint" },
              "rule": { "type": "string" }
            }, "additionalProperties": false },
            { "type": "object", "required": ["type", "command"], "properties": {
              "type": { "const": "command" },
              "command": { "type": "string" }
            }, "additionalProperties": false },
            { "type": "object", "required": ["type", "script"], "properties": {
              "type": { "const": "script" },
              "script": { "type": "string" }
            }, "additionalProperties": false },
            { "type": "object", "required": ["type"], "properties": {
              "type": { "const": "manual" },
              "rationale": { "type": "string" }
            }, "additionalProperties": false }
          ]
        },
        "examples": {
          "type": "object",
          "required": ["bad", "good"],
          "properties": {
            "bad": { "type": "string", "minLength": 1 },
            "good": { "type": "string", "minLength": 1 }
          }
        },
        "policy": {
          "type": "string",
          "description": "Free-form Markdown body for the rule"
        },
        "negative-test": {
          "type": "object",
          "required": ["input", "expect-violation"],
          "additionalProperties": false,
          "description": "Liveness data for ESLint-type rules: prove the guard catches its own bad corpus.",
          "properties": {
            "input": {
              "type": "array",
              "items": { "type": "string" },
              "minItems": 1,
              "description": "Code snippets that must each trigger the expected violation (bypass variants)."
            },
            "expect-violation": {
              "type": "string",
              "minLength": 1,
              "description": "ESLint messageId or ruleId expected from each input."
            },
            "eslintRuleConfig": {
              "description": "Optional ESLint rule config value, replacing bare 'error' for option-bearing rules (e.g. no-restricted-imports)."
            }
          }
        },
        "fixture": {
          "type": "object",
          "description": "Liveness data for command/script rules: a violating filesystem/env state the rule's check.command/check.script must exit-non-zero on. Presence is optional; v1.5 flips to required for command/script rules after migration.",
          "required": ["setup-script"],
          "additionalProperties": false,
          "properties": {
            "setup-script": {
              "type": "string",
              "minLength": 1,
              "description": "Shell commands that create the violating state. Must not be a trivial force-fail (e.g. `exit 1`)."
            },
            "cleanup-script": {
              "type": "string",
              "description": "Shell commands that restore the environment after the liveness probe."
            },
            "cwd": {
              "type": "string",
              "minLength": 1,
              "description": "Working directory for the setup and cleanup scripts."
            }
          }
        },
        "pressure-scenario": {
          "type": "object",
          "description": "RED→GREEN forcing-function data for the manual rule prober (v3). Presence is enforced as required for manual rules by principle 02 (the v3 flip); the schema keeps it optional so non-manual entries need not carry it.",
          "required": ["baseline-prompt", "observable-failure", "observable-compliance", "pressure"],
          "additionalProperties": false,
          "properties": {
            "baseline-prompt": {
              "type": "string",
              "minLength": 1,
              "description": "The AI prompt that, WITHOUT the rule enforced, produces the failing behaviour."
            },
            "observable-failure": {
              "type": "string",
              "minLength": 1,
              "description": "What the AI produces when the rule is NOT enforced (RED state)."
            },
            "observable-compliance": {
              "type": "string",
              "minLength": 1,
              "description": "What the AI produces when the rule IS enforced (GREEN state). Must differ from observable-failure."
            },
            "pressure": {
              "type": "array",
              "minItems": 1,
              "uniqueItems": true,
              "items": { "enum": ["time", "authority", "sunk-cost", "scope-creep"] },
              "description": "Which rationalizing pressure(s) the baseline-prompt applies (≥1). A scenario with no pressure is a violating example, not a forcing function (T-V3-A)."
            }
          }
        }
      }
    }
  },
  "additionalProperties": false
}
